{
  "contexts": [
    {
      "context": "Ощущение холодной керамики старой кофейной чашки в руках, когда пьешь остывший кофе в одиночестве на рассвете — и тоска по тому, чего уже не вернуть.",
      "added_at": "2026-06-29T07:21:12.807Z"
    },
    {
      "context": "Запах старого дерева в бабушкином сундуке — и внезапное ощущение забытого детства, полного шепота и секретов.",
      "added_at": "2026-06-30T06:44:51.815Z"
    },
    {
      "context": "Запах свежескошенной травы после дождя — и ощущение, что этот запах возвращает тебя в детство, к беззаботным дням, когда всё казалось простым и понятным.",
      "added_at": "2026-07-02T06:29:28.548Z"
    },
    {
      "context": "Запах мокрого асфальта после летнего дождя — и внезапное воспоминание о потерянном зонте, который она оставила на скамейке в парке, ожидая встречи, которой так и не произошло.",
      "added_at": "2026-07-03T06:21:04.171Z"
    },
    {
      "context": "Запах старых книг в бабушкиной библиотеке — и острое ощущение, что в них заключена целая жизнь, не прожитая тобой.",
      "added_at": "2026-07-04T06:08:56.973Z"
    },
    {
      "context": "Запах нагретого солнцем асфальта после дождя — и ощущение дежавю, как будто это уже происходило, много раз, но ты не можешь вспомнить когда.",
      "added_at": "2026-07-05T06:28:45.904Z"
    },
    {
      "context": "Мгновение, когда, зачерпывая воду из колодца, ты ощущаешь ледяное прикосновение металла к ладони — и внезапно вспоминаешь запах бабушкиных пирогов, и ощущение, что ты – дома, даже если дома давно нет.",
      "added_at": "2026-07-06T06:59:08.771Z"
    },
    {
      "context": "Запах старой ваты, которой когда-то заворачивали леденцы \"Пуговка\" – и внезапное воспоминание о тихом вечере, когда мама, уставшая после смены, сидела у окна и молча смотрела на снег.",
      "added_at": "2026-07-07T06:36:02.431Z"
    },
    {
      "context": "Запах старого дерева и пыли в заброшенном книжном магазине – и ощущение, что каждая книга хранит в себе чужую жизнь, чужие секреты, и ты можешь коснуться их, просто взяв книгу в руки.",
      "added_at": "2026-07-08T05:41:24.300Z"
    },
    {
      "context": "Внезапный, яркий солнечный луч, пробивающийся сквозь занавески в полутёмной комнате — и ощущение тепла на лице, которое напоминает о детстве, о летних днях, проведённых на бабушкиной веранде.",
      "added_at": "2026-07-10T06:31:52.595Z"
    },
    {
      "context": "Запах старых книг в бабушкином доме – и воспоминание о том, как она читала тебе сказки на ночь, чувствуя тепло её руки на твоей.",
      "added_at": "2026-07-11T05:31:42.128Z"
    },
    {
      "context": "Запах свежескошенной травы в сумерках — и ощущение, что это запах не лета, а потерянной юности, навсегда запечатленный в ткани времени.",
      "added_at": "2026-07-12T05:46:59.169Z"
    },
    {
      "context": "Запах нагретого солнцем асфальта после летнего дождя — и внезапное ощущение того, что ты снова стоишь на пороге чего-то нового, но боишься сделать первый шаг.",
      "added_at": "2026-07-13T05:57:15.905Z"
    },
    {
      "context": "Запах старой книги, открытой на случайной странице – и воспоминание о летнем дне, проведенном в бабушкиной библиотеке, когда весь мир казался огромным и полным тайн.",
      "added_at": "2026-07-14T05:20:30.267Z"
    },
    {
      "context": "Ощущение прохладного шёлка простыни, когда ты проваливаешься в ещё не наступившую ночь — и лёгкая тревога перед завтрашним днём.",
      "added_at": "2026-07-20T09:11:35.236Z"
    },
    {
      "context": "Вкус первого глотка чая, слишком горячего, обжигающего губы, — и мысль о том, кого ты давно не видел.",
      "added_at": "2026-07-20T09:11:35.236Z"
    },
    {
      "context": "Скрип старой двери на даче, открывающейся в сад, где уже давно никто не живёт.",
      "added_at": "2026-07-20T09:11:35.236Z"
    },
    {
      "context": "Мерцание свечи на подоконнике, отражающееся в дождевых каплях на стекле, — и тишина, звенящая в ушах.",
      "added_at": "2026-07-20T09:11:35.236Z"
    },
    {
      "context": "Прикосновение к пожелтевшему письму, написанному чужой рукой много лет назад, — и догадка, что его автор забыт всеми.",
      "added_at": "2026-07-20T09:11:35.236Z"
    },
    {
      "context": "Звук далёкого поезда за окном в полночь — и внезапное чувство, что жизнь проходит мимо тебя.",
      "added_at": "2026-07-20T09:11:35.236Z"
    },
    {
      "context": "Ощущение песка, набившегося в босые сандалии после прогулки по пустому пляжу поздней осенью.",
      "added_at": "2026-07-20T09:11:35.236Z"
    },
    {
      "context": "Запах гари от сгоревшей спички, которой ты зажёг свечу, — и короткое воспоминание о человеке, с которым больше не говоришь.",
      "added_at": "2026-07-20T09:11:35.236Z"
    },
    {
      "context": "Холод ледяной ручки крана ранним утром и резкий контраст с теплом собственного дыхания.",
      "added_at": "2026-07-20T09:11:35.236Z"
    },
    {
      "context": "Вид теней от веток на потолке при свете фонаря — и ощущение, будто комната дышит вместе с тобой.",
      "added_at": "2026-07-20T09:11:35.236Z"
    },
    {
      "context": "Вкус кислого яблока из старого сада, где деревья выше, чем ты помнишь, — и горечь чего-то несбывшегося.",
      "added_at": "2026-07-20T09:11:35.236Z"
    },
    {
      "context": "Шелест страниц, которые ты перечитываешь снова и снова, потому что боишься забыть, о чём они.",
      "added_at": "2026-07-20T09:11:35.236Z"
    },
    {
      "context": "Ощущение тяжести шерстяного пледа, укутавшего плечи, когда за окном завывает первый зимний ветер.",
      "added_at": "2026-07-20T09:11:35.236Z"
    },
    {
      "context": "Запах мяты и лимона на кухне вечером — и тихое понимание, что счастье было в обыденности, которую ты не ценил.",
      "added_at": "2026-07-20T09:11:35.236Z"
    },
    {
      "context": "Отблеск луны на лужах после дождя, превращающий асфальт в зеркало, в котором ты не узнаёшь себя.",
      "added_at": "2026-07-20T09:11:35.236Z"
    },
    {
      "context": "Звук собственного голоса, читающего вслух в пустой комнате, — и странное утешение в этом эхе.",
      "added_at": "2026-07-20T09:11:35.236Z"
    }
  ]
}